veracitysdk/__init__.py
veracitysdk/responses.py
veracitysdk/models/__init__.py
veracitysdk/models/articles.py
veracitysdk/models/base.py
veracitysdk/models/classifiers.py
veracitysdk/models/domains.py
veracitysdk/models/tags.py
veracitysdk-0.1.14.dist-info/LICENSE
veracitysdk-0.1.14.dist-info/WHEEL
veracitysdk-0.1.14.dist-info/METADATA
veracitysdk-0.1.14.dist-info/RECORD
